setup.cfg
setup.py
ticks.py
ticks.egg-info/PKG-INFO
ticks.egg-info/SOURCES.txt
ticks.egg-info/dependency_links.txt
ticks.egg-info/entry_points.txt
ticks.egg-info/requires.txt
ticks.egg-info/top_level.txt