Metadata-Version: 1.0
Name: ticks
Version: 0.1.5
Summary: Command line stock ticker
Home-page: https://github.com/jamescnowell/ticks
Author: James Nowell
Author-email: jnowell129@gmail.com
License: WTFPL
Platform: UNKNOWN
